{"version":"v2.0","snapshotAtUtc":"2026-04-11T14:00:00Z","generatedAtUtc":"2026-04-11T14:11:00Z","ticker":["‘Michael’ Moonwalks To Top Of Mogul Hype Index As Trailer Views Spike Heading Into Weekend","Super Mario Galaxy Movie Levels Up Again, Holding Near-Perfect AMSI On Back Of Casting And Director Rumors","Milly Alcock Cemented As Breakout Lead; Social Sentiment Crowns Her New-Gen Fantasy Franchise Queen","Zendaya Avengers Spec Heats Up The Town, With Destin Daniel Cretton Package Drawing Multiple Studio Meetings","Awards Heat For The Drama Surges As Test Screening Buzz And Blogger Discourse Drive Double-Digit NIS Gain","Dune: Messiah And Spider-Man 4 Trade Places In Franchise Derby As Fans Debate Which Event Pic Lands First","Antoine Fuqua Rides Michael Wave, Notching Cycle-High Director AMSI Off Biopic Buzz","Greta Gerwig-Nintendo Chatter Keeps Super Mario Galaxy Movie Firmly In Family-Tentpole Pole Position"],"tabs":{"movies":[{"rank":1,"name":"Michael (2026)","move":0,"mentions":18500,"sentiment":99,"score":999.0},{"rank":2,"name":"Super Mario Galaxy Movie","move":0,"mentions":17900,"sentiment":98,"score":998.5},{"rank":3,"name":"The Drama","move":3,"mentions":14320,"sentiment":96,"score":957.3},{"rank":4,"name":"Dune: Messiah","move":-1,"mentions":13640,"sentiment":93,"score":948.9},{"rank":5,"name":"Spider-Man 4","move":-1,"mentions":12980,"sentiment":90,"score":944.7}],"actors":[{"rank":1,"name":"Milly Alcock","move":0,"mentions":15210,"sentiment":98,"score":966.2},{"rank":2,"name":"Zendaya","move":2,"mentions":18840,"sentiment":95,"score":963.8},{"rank":3,"name":"Pedro Pascal","move":-1,"mentions":14130,"sentiment":94,"score":952.1},{"rank":4,"name":"Timothée Chalamet","move":-1,"mentions":13220,"sentiment":91,"score":946.4},{"rank":5,"name":"Anya Taylor-Joy","move":1,"mentions":11980,"sentiment":90,"score":939.6}],"directors":[{"rank":1,"name":"Antoine Fuqua","move":1,"mentions":9270,"sentiment":96,"score":955.5},{"rank":2,"name":"Greta Gerwig","move":2,"mentions":9910,"sentiment":95,"score":952.7},{"rank":3,"name":"Destin Daniel Cretton","move":4,"mentions":8740,"sentiment":94,"score":948.3},{"rank":4,"name":"Alfonso Cuarón","move":2,"mentions":7620,"sentiment":93,"score":944.9},{"rank":5,"name":"Jon Watts","move":-3,"mentions":7130,"sentiment":90,"score":937.2}]}}